LICENSE
MANIFEST.in
README.rst
setup.py
cache_decorator/__init__.py
cache_decorator/__version__.py
cache_decorator/cache.py
cache_decorator.egg-info/PKG-INFO
cache_decorator.egg-info/SOURCES.txt
cache_decorator.egg-info/dependency_links.txt
cache_decorator.egg-info/requires.txt
cache_decorator.egg-info/top_level.txt
cache_decorator/backends/__init__.py
cache_decorator/backends/backend.py
cache_decorator/backends/backend_template.py
cache_decorator/backends/compress_json_backend.py
cache_decorator/backends/compress_pickle_backend.py
cache_decorator/backends/exceptions.py
cache_decorator/backends/json_backend.py
cache_decorator/backends/keras_model_backend.py
cache_decorator/backends/numpy_backend.py
cache_decorator/backends/pandas_csv_backend.py
cache_decorator/backends/pandas_embedding_backend.py
cache_decorator/backends/pickle_backend.py
cache_decorator/backends/txt_backend.py
cache_decorator/utils/__init__.py
cache_decorator/utils/get_format_groups.py
cache_decorator/utils/get_params.py
cache_decorator/utils/parse_time.py
cache_decorator/utils/random_string.py
tests/test_capture_enable_arg_name.py
tests/test_compute_path.py
tests/test_csv.py
tests/test_csv_bz2.py
tests/test_csv_gz.py
tests/test_csv_with_tuple_columns.py
tests/test_csv_xz.py
tests/test_csv_zip.py
tests/test_duration_missing_path.py
tests/test_duration_validity.py
tests/test_embedding.py
tests/test_empty_folder.py
tests/test_enable_cache_arg_name.py
tests/test_exception.py
tests/test_fmt_cache_dir.py
tests/test_get_params.py
tests/test_getattr_path.py
tests/test_ignore_args.py
tests/test_ignore_args_method.py
tests/test_ignore_kwargs.py
tests/test_json.py
tests/test_json_bz.py
tests/test_json_gz.py
tests/test_json_lzma.py
tests/test_keras_model.py
tests/test_kwargs.py
tests/test_load_store.py
tests/test_luca.py
tests/test_method.py
tests/test_npy.py
tests/test_npz.py
tests/test_numpy_csv.py
tests/test_optional_path_keys.py
tests/test_parse_time.py
tests/test_pickle.py
tests/test_pickle_bz.py
tests/test_pickle_gz.py
tests/test_pickle_lzma.py
tests/test_pickle_zip.py
tests/test_static_class_property_methods.py
tests/test_structured_paths.py
tests/test_tsv.py
tests/test_txt.py
