Metadata-Version: 2.1
Name: cache-decorator
Version: 2.2.0
Summary: a simple decorator to cache the results of computationally heavy functions
Home-page: https://github.com/zommiommy/cache_decorator
Author: Tommaso Fontana
Author-email: tommaso.fontana.96@gmail.com
License: MIT
Classifier: Development Status :: 3 - Alpha
Classifier: License :: OSI Approved :: MIT License
Classifier: Programming Language :: Python :: 3
License-File: LICENSE
